{
  "guncellenme_tarihi": "2026-05-06",
  "fonlar": {
    "AAL": 3.201588,
    "AAS": 11.690012,
    "AAV": 62.081652,
    "ABG": 61.397425,
    "ABJ": 0.849023,
    "ABU": 0.0945,
    "AC1": 2.885873,
    "AC2": 3.62741,
    "AC3": 66.245744,
    "AC4": 3.543527,
    "AC5": 3.441425,
    "AC6": 55.864036,
    "AC7": 10.541389,
    "AC8": 194.720307,
    "ACC": 44.378385,
    "ACD": 5.511441,
    "ACN": 11.79058,
    "ACU": 52.983027,
    "ADE": 0.86434,
    "ADP": 1.277102,
    "AED": 109.179827,
    "AES": 0.181887,
    "AEV": 1.957896,
    "AFA": 1.118409,
    "AFO": 1.310961,
    "AFS": 0.303162,
    "AFT": 0.944432,
    "AFV": 0.531989,
    "AGC": 8.707009,
    "AHH": 9.674103,
    "AHI": 37.264939,
    "AHN": 66.193372,
    "AHU": 10.223314,
    "AHV": 19.912819,
    "AHZ": 27.189445,
    "AI1": 1.119026,
    "AIH": 17.670428,
    "AII": 89.591772,
    "AIM": 24.822087,
    "AIR": 153.53129,
    "AIS": 0.095882,
    "AJ1": 1.212183,
    "AJE": 59.043997,
    "AJK": 60.391751,
    "AJL": 60.03938,
    "AJN": 58.25765,
    "AK2": 0.500524,
    "AK3": 53.966856,
    "AKE": 0.490503,
    "AKU": 0.949055,
    "AL4": 3.570122,
    "AL5": 50.621322,
    "AL6": 3.490936,
    "AL7": 3.373969,
    "ALC": 0.374044,
    "ALE": 12.062793,
    "AN1": 100.420955,
    "ANL": 33.447824,
    "ANZ": 20.418635,
    "AOJ": 1.594834,
    "AOY": 0.371968,
    "AP2": 3.687493,
    "AP4": 1.364995,
    "AP5": 0.999169,
    "AP6": 8.539722,
    "AP7": 2.347255,
    "APJ": 6.907807,
    "APP": 31.814536,
    "APT": 0.146698,
    "ARE": 0.225174,
    "ARF": 7.878439,
    "ARL": 15.031019,
    "ARM": 17.772067,
    "ARP": 40.116516,
    "AS1": 45.191253,
    "AS3": 0.752447,
    "ASJ": 3.817252,
    "ATJ": 22.468733,
    "AU1": 1.154855,
    "AUV": 46.292564,
    "AVC": 145.29958,
    "AVT": 202.185967,
    "AVZ": 96.428109,
    "AY6": 1.317366,
    "AY7": 1.494546,
    "AYA": 18.99589,
    "AYR": 0.12522,
    "AZF": 0.16511,
    "AZJ": 18.28823,
    "AZV": 25.063281,
    "AZZ": 59.34613,
    "BA1": 1.44641,
    "BAC": 5.710699,
    "BAG": 0.932993,
    "BAL": 46.663235,
    "BAO": 3.273305,
    "BAS": 50.291626,
    "BBF": 3.212896,
    "BBI": 1.557532,
    "BBN": 0.652367,
    "BBO": 2.437946,
    "BBP": 2.041638,
    "BBS": 1.406443,
    "BCC": 64.943833,
    "BCK": 1.894018,
    "BCO": 1.722567,
    "BDA": 53.432105,
    "BDC": 9.094661,
    "BDI": 0.632099,
    "BDO": 2.903079,
    "BDS": 2.486941,
    "BDY": 1.645209,
    "BFE": 1.743894,
    "BFO": 49.985296,
    "BFS": 1.019934,
    "BFT": 1.141294,
    "BGH": 2.252262,
    "BGP": 5.825843,
    "BHA": 1.555402,
    "BHE": 1.968878,
    "BHF": 3.000333,
    "BHH": 0.681563,
    "BHI": 2.103502,
    "BHL": 1.256245,
    "BHO": 1.130467,
    "BI5": 2.751126,
    "BIA": 0.213185,
    "BID": 3.357275,
    "BIG": 1.399374,
    "BIH": 7.695567,
    "BIK": 1.465019,
    "BIO": 2.448811,
    "BIP": 1.458195,
    "BIS": 1.639035,
    "BIY": 1.285297,
    "BJD": 49.815778,
    "BKO": 1.142903,
    "BKY": 46.293794,
    "BLA": 7.035283,
    "BLD": 1.489153,
    "BLT": 1.708784,
    "BMU": 1.628686,
    "BNC": 1.976584,
    "BNH": 1.226522,
    "BOH": 0.939715,
    "BOL": 1.547465,
    "BON": 1.242387,
    "BOP": 45.950025,
    "BOS": 1.355934,
    "BP5": 1.894084,
    "BPD": 50.102505,
    "BPZ": 1.397151,
    "BRB": 1.285181,
    "BRC": 1.219854,
    "BRF": 1.505376,
    "BRG": 4.564398,
    "BRH": 5.842281,
    "BRR": 1.477746,
    "BRT": 1.235311,
    "BRZ": 51.11247,
    "BS1": 1.164542,
    "BSA": 0.419813,
    "BSD": 1.11308,
    "BSE": 0.733733,
    "BSF": 1.325461,
    "BSH": 1.017116,
    "BSM": 1.482643,
    "BSN": 1.61629,
    "BST": 10.161773,
    "BTE": 4.229013,
    "BTJ": 1.25564,
    "BTK": 1.410909,
    "BTP": 0.516623,
    "BTY": 54.89486,
    "BTZ": 1.280936,
    "BUB": 1.039659,
    "BUC": 0.974957,
    "BUP": 3.775482,
    "BUT": 1.746163,
    "BUV": 1.369622,
    "BUY": 1.843046,
    "BV1": 1.550116,
    "BVB": 4.092732,
    "BVC": 3.89159,
    "BVD": 1.217578,
    "BVF": 1.255451,
    "BVH": 1.851399,
    "BVI": 2.944425,
    "BVK": 1.125662,
    "BVM": 1.322081,
    "BVT": 5.175886,
    "BVV": 2.99832,
    "BVZ": 4.011218,
    "BYZ": 2.135298,
    "CAH": 1.338954,
    "CBD": 1.760407,
    "CBN": 48.639835,
    "CBO": 262.203091,
    "CEY": 62.136402,
    "CFO": 2.242587,
    "CGD": 54.195375,
    "CHY": 0.668325,
    "CIN": 1.627956,
    "CJD": 47.993814,
    "CJF": 61.053492,
    "CJG": 61.343791,
    "CJH": 58.48346,
    "CKF": 1.892966,
    "CKL": 1.416621,
    "CKS": 57.063456,
    "COT": 55.697926,
    "CPT": 3.494407,
    "CPU": 3.33287,
    "CRL": 45.609061,
    "CSD": 60.177124,
    "CSH": 3.923293,
    "CTF": 8.689311,
    "CTG": 7.116321,
    "CTM": 5.970717,
    "CTP": 58.264908,
    "CTV": 10.13455,
    "CVA": 3.714662,
    "CVB": 3.848372,
    "CVC": 2.612369,
    "CVD": 59.532954,
    "CVE": 2.45698,
    "CVF": 4.233375,
    "CVK": 4.689219,
    "CVL": 1.243071,
    "CYD": 54.574437,
    "DA1": 46.346199,
    "DAC": 67.882842,
    "DAE": 4.021501,
    "DAH": 3.673498,
    "DAI": 89.569535,
    "DAL": 66.137756,
    "DAS": 51.441022,
    "DAT": 91.044295,
    "DAV": 54.708686,
    "DAZ": 12.18875,
    "DB2": 1.869248,
    "DBA": 0.732455,
    "DBB": 0.102157,
    "DBG": 0.585284,
    "DBH": 0.353991,
    "DBK": 0.108391,
    "DBP": 0.468469,
    "DBZ": 0.125768,
    "DCB": 4.246671,
    "DCD": 62.070946,
    "DCE": 68.176828,
    "DCN": 1.285285,
    "DCP": 69.775731,
    "DDA": 12.818342,
    "DDC": 12.590301,
    "DDE": 70.99367,
    "DDF": 11.022381,
    "DDP": 68.812471,
    "DEF": 2.560384,
    "DEI": 0.03492,
    "DFC": 3.178773,
    "DFD": 2.654452,
    "DFI": 3.841951,
    "DFO": 3.523713,
    "DGF": 1.291621,
    "DGH": 9.579814,
    "DHI": 3.788743,
    "DHJ": 7.545032,
    "DHM": 5.155755,
    "DHP": 3.57571,
    "DHS": 325.635161,
    "DHT": 1.046271,
    "DHV": 2.247482,
    "DID": 1.359125,
    "DIH": 1.896924,
    "DIM": 48.840295,
    "DIP": 1.403592,
    "DK1": 1.332066,
    "DK8": 45.049614,
    "DKA": 44.980333,
    "DKC": 0.641464,
    "DKH": 3.692995,
    "DKL": 47.341773,
    "DKP": 45.307224,
    "DKR": 0.726402,
    "DKS": 67.436176,
    "DKY": 45.16674,
    "DL2": 2.211033,
    "DLD": 7.157594,
    "DLG": 1.190208,
    "DLN": 1.919205,
    "DLY": 5.425919,
    "DLZ": 1.144687,
    "DMG": 7.284353,
    "DMR": 54.604439,
    "DMV": 65.587959,
    "DMZ": 59.95624,
    "DNA": 9.403505,
    "DNF": 1.193608,
    "DNH": 1.189448,
    "DNK": 1.698117,
    "DNL": 52.047955,
    "DNM": 48.421989,
    "DNP": 1.280813,
    "DNU": 44.948291,
    "DOC": 45.024794,
    "DOD": 64.210592,
    "DOH": 2.018389,
    "DOL": 49.223966,
    "DOR": 66.506812,
    "DOS": 65.420324,
    "DOV": 57.151989,
    "DP1": 17.825951,
    "DP2": 62.723902,
    "DP3": 65.083857,
    "DP4": 68.228947,
    "DP5": 75.451519,
    "DP6": 45.08527,
    "DP7": 56.934967,
    "DP8": 45.394465,
    "DP9": 45.129314,
    "DPB": 22.728653,
    "DPC": 92.573833,
    "DPE": 21.088218,
    "DPG": 93.640789,
    "DPI": 7.997093,
    "DPK": 7.771111,
    "DPL": 96.209237,
    "DPN": 56.449867,
    "DPP": 155.902859,
    "DPT": 17.322046,
    "DPZ": 76.939414,
    "DRA": 1.160692,
    "DRD": 52.977163,
    "DRH": 1.122646,
    "DRS": 69.604249,
    "DRT": 1.138116,
    "DSC": 62.288095,
    "DSD": 67.013004,
    "DSH": 2.034682,
    "DSP": 13.645977,
    "DSV": 45.929853,
    "DTH": 1.32637,
    "DTL": 4.015025,
    "DTM": 1.376143,
    "DTO": 45.074102,
    "DTP": 1.853937,
    "DTV": 63.836727,
    "DTZ": 4.709441,
    "DUC": 0.625325,
    "DUD": 48.029852,
    "DUH": 1.014376,
    "DUT": 45.036568,
    "DUV": 1.1951,
    "DVC": 63.913303,
    "DVI": 72.51779,
    "DVN": 60.975205,
    "DVO": 4.781592,
    "DVS": 1.402716,
    "DVT": 8.691402,
    "DVU": 7.734299,
    "DVZ": 61.911273,
    "DXP": 1.81936,
    "DYJ": 45.235843,
    "DYN": 4.483268,
    "DYS": 1.504009,
    "DZ2": 1.388559,
    "DZE": 1.005047,
    "DZM": 80.723331,
    "DZP": 56.492248,
    "DZS": 1.412467,
    "EBD": 0.239162,
    "EBI": 53.123391,
    "EBS": 45.68657,
    "EC2": 88.027894,
    "ECA": 1.700553,
    "ECB": 47.761088,
    "ECV": 0.439049,
    "EDD": 1.055844,
    "EDP": 1.037339,
    "EDT": 2.015782,
    "EDU": 3.289713,
    "EES": 54.922281,
    "EGP": 54.148399,
    "EHS": 2.736155,
    "EIB": 0.587431,
    "EID": 1.844515,
    "EIL": 4.691533,
    "EJG": 9.69889,
    "EKF": 0.126255,
    "EKL": 1.631906,
    "ELZ": 14.018842,
    "EME": 1.203915,
    "EML": 1.181794,
    "ENA": 1.05377,
    "ENJ": 1.38408,
    "ENO": 45.301493,
    "ENR": 1.073097,
    "ENS": 1.095989,
    "EPA": 1.229128,
    "EPI": 1.157186,
    "EPK": 1.401423,
    "EPO": 57.806961,
    "EPP": 1.315542,
    "EPT": 1.190061,
    "ESG": 4.12168,
    "ESN": 1.658738,
    "ESP": 0.519285,
    "EUN": 59.632732,
    "EUZ": 59.287503,
    "EVM": 1.089243,
    "EYT": 2.788768,
    "EZM": 42.296767,
    "FAK": 1.352248,
    "FAL": 1.228172,
    "FBC": 2.259821,
    "FBI": 49.506689,
    "FBN": 10.476222,
    "FBV": 7.19452,
    "FBZ": 4.232006,
    "FCK": 1.954315,
    "FCS": 2.065392,
    "FD1": 1.820633,
    "FDE": 45.259779,
    "FDG": 2.825037,
    "FDO": 57.282815,
    "FDV": 5.307942,
    "FDY": 45.401882,
    "FDZ": 0.343469,
    "FFD": 0.045585,
    "FFF": 62.569811,
    "FFH": 7.977893,
    "FFO": 58.224809,
    "FFP": 7.342585,
    "FHI": 1.542854,
    "FHP": 3.027751,
    "FHZ": 62.359509,
    "FI3": 727.008417,
    "FI5": 662.270927,
    "FIB": 0.500125,
    "FID": 1.002975,
    "FIL": 0.331591,
    "FIT": 0.21229,
    "FJB": 6.595967,
    "FJC": 55.942152,
    "FJM": 53.93431,
    "FJN": 53.740202,
    "FJZ": 61.781055,
    "FKE": 56.062365,
    "FKH": 45.790725,
    "FKV": 45.407081,
    "FLS": 57.805672,
    "FLY": 1.608255,
    "FMG": 3.587665,
    "FMS": 53.761238,
    "FMV": 1.270509,
    "FNE": 2.744335,
    "FNN": 0.0,
    "FNO": 0.189023,
    "FNT": 2.04022,
    "FP4": 1.287365,
    "FPE": 71.006893,
    "FPG": 2.359765,
    "FPH": 33.859991,
    "FPI": 2.362631,
    "FPK": 0.088179,
    "FPR": 11.159889,
    "FPZ": 64.537047,
    "FR1": 1.276438,
    "FRA": 32.34095,
    "FRC": 1.917552,
    "FRZ": 15.309128,
    "FS1": 1.802552,
    "FS2": 2.04479,
    "FS3": 1.871802,
    "FS4": 6.962523,
    "FS5": 2.535175,
    "FS6": 1.568699,
    "FSF": 6.165646,
    "FSG": 3.720167,
    "FSH": 4.289326,
    "FSK": 5.457848,
    "FSM": 10.199404,
    "FSP": 37.318848,
    "FSR": 44.954725,
    "FSU": 1.332166,
    "FSV": 52.972464,
    "FTL": 1.367654,
    "FTM": 52.479859,
    "FTY": 45.227577,
    "FUA": 5.434733,
    "FUB": 0.704226,
    "FUM": 58.769588,
    "FUN": 1.480168,
    "FUP": 102.387722,
    "FVL": 4.414522,
    "FYA": 0.054256,
    "FYB": 94.168357,
    "FYD": 11.800213,
    "FYF": 0.099974,
    "FYG": 15.611441,
    "FYH": 82.513389,
    "FYI": 9.004014,
    "FYM": 0.411065,
    "FYO": 1.060717,
    "FYT": 0.327767,
    "FYZ": 6.249678,
    "FZJ": 5.248222,
    "FZP": 6.076376,
    "GA1": 1.797086,
    "GAC": 71.316499,
    "GAE": 0.462419,
    "GAF": 1.722624,
    "GAG": 16.876427,
    "GAH": 11.631417,
    "GAJ": 59.205709,
    "GAL": 366.808104,
    "GAN": 9.701185,
    "GAS": 0.297216,
    "GAU": 61.584292,
    "GAV": 57.429531,
    "GBC": 0.287749,
    "GBG": 0.529576,
    "GBH": 4.162876,
    "GBJ": 1.466403,
    "GBL": 0.77663,
    "GBN": 6.142655,
    "GBP": 66.20943,
    "GBV": 11.906443,
    "GBZ": 3.45359,
    "GCA": 67.087535,
    "GCC": 5.361551,
    "GCD": 3.218198,
    "GCI": 60.206918,
    "GCZ": 57.81733,
    "GDJ": 57.330897,
    "GDP": 62.13307,
    "GEC": 71.259822,
    "GEI": 81.204831,
    "GEZ": 56.653206,
    "GFB": 65.381515,
    "GFD": 64.888594,
    "GFI": 50.024117,
    "GFL": 11.17528,
    "GFN": 73.505818,
    "GFY": 64.544071,
    "GGA": 62.711989,
    "GGC": 5.241113,
    "GGD": 61.419571,
    "GGK": 13.702955,
    "GGM": 7.551627,
    "GGN": 64.170955,
    "GGP": 25.922496,
    "GGR": 63.46064,
    "GHS": 39.638567,
    "GID": 1.669706,
    "GIE": 3.617298,
    "GIH": 2.496563,
    "GJA": 61.665281,
    "GJB": 10.296103,
    "GJD": 59.381161,
    "GJE": 58.854804,
    "GJF": 59.644115,
    "GJH": 3.512217,
    "GJM": 37.111336,
    "GJO": 55.78389,
    "GKE": 0.0,
    "GKF": 4.861695,
    "GKG": 1.400391,
    "GKH": 4.008402,
    "GKK": 61.08498,
    "GKL": 15.117925,
    "GKM": 45.567624,
    "GKO": 0.0,
    "GKV": 8.030313,
    "GL1": 1433.460479,
    "GLC": 4.219495,
    "GLG": 8.567654,
    "GLM": 0.53714,
    "GLP": 63.350152,
    "GLS": 0.153271,
    "GLV": 8.399161,
    "GMA": 1.960635,
    "GMC": 8.559396,
    "GMD": 2.584651,
    "GME": 26.830819,
    "GMI": 1.48597,
    "GMM": 45.304628,
    "GMN": 1.219441,
    "GMO": 2.908617,
    "GMP": 57.852192,
    "GMR": 1.408803,
    "GMV": 0.0,
    "GMZ": 13.148954,
    "GNH": 1.518053,
    "GNK": 64.54997,
    "GNL": 56.636561,
    "GNP": 1.318224,
    "GNS": 1.582732,
    "GNZ": 1.472603,
    "GO1": 4.308434,
    "GO2": 4.624115,
    "GO3": 4.694591,
    "GO4": 5.072924,
    "GO6": 3.766548,
    "GO9": 2.547726,
    "GOF": 48.985957,
    "GOH": 16.278267,
    "GOL": 2.770094,
    "GOP": 1.081371,
    "GP1": 3.891782,
    "GP3": 57.554961,
    "GPA": 21.545739,
    "GPB": 11.197995,
    "GPC": 67.05784,
    "GPF": 8.357056,
    "GPG": 14.152048,
    "GPH": 43.441186,
    "GPI": 16.999122,
    "GPJ": 54.097541,
    "GPL": 49.68837,
    "GPM": 58.028292,
    "GPN": 1.240613,
    "GPT": 2.584375,
    "GPU": 19.752878,
    "GPV": 62.976505,
    "GPZ": 1.75076,
    "GRL": 1.740497,
    "GRO": 50.597001,
    "GRT": 1.668784,
    "GSE": 60.291809,
    "GSG": 66.620465,
    "GSL": 3.071475,
    "GSO": 13.628817,
    "GSP": 0.553493,
    "GSR": 53.200668,
    "GSU": 0.0,
    "GTA": 1.578763,
    "GTF": 13.605493,
    "GTH": 1.326873,
    "GTK": 6.36557,
    "GTL": 0.120316,
    "GTM": 7.933553,
    "GTN": 48.85644,
    "GTY": 5.812432,
    "GTZ": 12.697095,
    "GUA": 5.46956,
    "GUB": 2.294799,
    "GUC": 1.305094,
    "GUH": 0.389973,
    "GUK": 1.532569,
    "GUM": 13.555851,
    "GUV": 1.58507,
    "GVA": 4.249418,
    "GVB": 63.317442,
    "GVC": 60.15835,
    "GVD": 19.81787,
    "GVI": 5.456394,
    "GVL": 62.233141,
    "GVZ": 68.445138,
    "GYC": 3.704917,
    "GYG": 66.867466,
    "GYK": 0.102665,
    "GYL": 13.041518,
    "GYN": 62.878289,
    "GYR": 58.888112,
    "GZB": 6.675088,
    "GZD": 57.826907,
    "GZE": 7.463006,
    "GZG": 5.931218,
    "GZH": 5.180278,
    "GZJ": 8.248268,
    "GZL": 5.320364,
    "GZM": 8.415196,
    "GZN": 44.690497,
    "GZO": 65.445605,
    "GZP": 7.095022,
    "GZR": 11.701466,
    "GZU": 63.250346,
    "GZV": 8.02348,
    "GZY": 7.004946,
    "GZZ": 6.427975,
    "HAE": 52.396248,
    "HAG": 57.99988,
    "HAM": 3.065081,
    "HAR": 1.121404,
    "HAT": 1.803022,
    "HB1": 47.201772,
    "HB2": 54.501241,
    "HBF": 50.207074,
    "HBJ": 2.37171,
    "HBN": 4.072633,
    "HBU": 1.472446,
    "HBV": 16.775836,
    "HCV": 0.997488,
    "HDA": 2.859134,
    "HDE": 54.336001,
    "HDH": 9082.400349,
    "HDJ": 5.842906,
    "HDK": 2.80913,
    "HDS": 15.505622,
    "HDV": 62.232933,
    "HEH": 2.942763,
    "HFA": 2.930749,
    "HFI": 1.662187,
    "HFR": 1.501241,
    "HFV": 59.516751,
    "HFY": 1.174592,
    "HGC": 49.55416,
    "HGH": 1.901044,
    "HGJ": 13.420599,
    "HGM": 4.028283,
    "HGR": 1.202463,
    "HGT": 88.77897,
    "HGU": 4.501137,
    "HGV": 5.349577,
    "HIA": 1.393832,
    "HIF": 0.627507,
    "HIH": 1.424039,
    "HII": 3.09969,
    "HIM": 3.611678,
    "HIP": 1.932305,
    "HIS": 3.452124,
    "HIZ": 1.938106,
    "HJA": 28.878252,
    "HJB": 4.393718,
    "HKG": 1.393992,
    "HKH": 8.534042,
    "HKJ": 1.23596,
    "HKM": 4.695795,
    "HKP": 5.71978,
    "HKR": 4.038779,
    "HKV": 528.230047,
    "HLA": 2.026019,
    "HLL": 0.340634,
    "HLR": 221.147995,
    "HMC": 7.247214,
    "HME": 50.830297,
    "HMG": 0.061324,
    "HMK": 307.591769,
    "HML": 46.097081,
    "HMS": 0.102387,
    "HMT": 6.808012,
    "HMV": 19.130239,
    "HNC": 1.395008,
    "HNS": 46.733298,
    "HOA": 0.223227,
    "HOY": 0.332928,
    "HP3": 54.417127,
    "HPC": 11.408024,
    "HPD": 0.212205,
    "HPF": 31.985324,
    "HPH": 2.13325,
    "HPI": 8.415103,
    "HPJ": 3.699129,
    "HPL": 2.512623,
    "HPO": 0.154013,
    "HPT": 0.101589,
    "HPV": 6.976961,
    "HPZ": 580.259333,
    "HRZ": 2.30805,
    "HSA": 1564.122708,
    "HSL": 368.317757,
    "HSP": 44.302494,
    "HST": 0.915837,
    "HTF": 1.291355,
    "HTJ": 1.719691,
    "HTS": 53.477323,
    "HTZ": 15.320435,
    "HUI": 92.556511,
    "HUS": 0.003617,
    "HVA": 278.574955,
    "HVB": 1.803398,
    "HVC": 24.817082,
    "HVI": 1.268537,
    "HVK": 5.123196,
    "HVL": 20.406615,
    "HVN": 5.413021,
    "HVS": 1.597644,
    "HVT": 4.191285,
    "HVU": 5.373234,
    "HVV": 64.918353,
    "HVZ": 6.952992,
    "HYK": 10.12838,
    "HYP": 9.31285,
    "HYU": 1.608033,
    "HYV": 5.655058,
    "HYY": 11.993287,
    "HZV": 5.772027,
    "IAC": 4.140945,
    "IAE": 1.976773,
    "IAF": 0.884764,
    "IAI": 6.543943,
    "IAM": 1.661093,
    "IAR": 72.304997,
    "IAS": 2.228638,
    "IAT": 0.17871,
    "IAU": 2.406017,
    "IAY": 1.489148,
    "IBB": 14.216587,
    "IBC": 17.480615,
    "IBE": 22.233835,
    "IBG": 1.461773,
    "IBJ": 60.7573,
    "IBK": 0.122284,
    "IBM": 3.577882,
    "IBP": 64.578971,
    "IBR": 0.266235,
    "ICA": 0.546205,
    "ICC": 1.276478,
    "ICD": 121.872703,
    "ICE": 114.166599,
    "ICF": 187.858431,
    "ICG": 65.681609,
    "ICH": 2.035103,
    "ICN": 3.777525,
    "ICS": 47.909676,
    "ICV": 5.528127,
    "ICZ": 8.647104,
    "IDD": 0.15074,
    "IDF": 71.985696,
    "IDH": 12.811152,
    "IDI": 1.52727,
    "IDL": 5.380066,
    "IDO": 55.003319,
    "IDP": 2.043412,
    "IDV": 66.182213,
    "IDY": 0.215713,
    "IED": 1.003354,
    "IEN": 1.287596,
    "IEV": 4.703922,
    "IEZ": 5.601399,
    "IFD": 56.184054,
    "IFN": 9.571038,
    "IFV": 4.171131,
    "IFY": 6.857024,
    "IGF": 63.380216,
    "IGL": 517.025031,
    "IGM": 61.815183,
    "IGZ": 10.551897,
    "IHA": 3.21793,
    "IHC": 6.498186,
    "IHK": 17.011331,
    "IHP": 1.727541,
    "IHT": 3.73086,
    "IHV": 1.88121,
    "IHY": 7.088995,
    "IHZ": 1.024327,
    "IIA": 6.054182,
    "IIC": 3.29103,
    "IIE": 8.841196,
    "IIF": 1.327419,
    "IIH": 32.987942,
    "IIN": 1.247588,
    "IIP": 0.324191,
    "IIS": 0.0,
    "IJA": 13.341607,
    "IJB": 5.906382,
    "IJC": 15.512713,
    "IJE": 63.428519,
    "IJF": 9.936444,
    "IJH": 6.700159,
    "IJI": 10.125501,
    "IJK": 59.707747,
    "IJL": 50.557302,
    "IJP": 8.104355,
    "IJT": 6.748151,
    "IJV": 5.025364,
    "IJZ": 11.280642,
    "IK2": 44.908607,
    "IKL": 8.737077,
    "IKP": 9.006582,
    "IKV": 1.373428,
    "ILC": 47.780129,
    "ILE": 4.610654,
    "ILH": 3.563847,
    "ILI": 5.218326,
    "ILM": 7.105749,
    "ILP": 58.149229,
    "ILU": 1.110351,
    "ILZ": 7.569936,
    "IMB": 1.229409,
    "IMF": 5.300123,
    "IMG": 46.459443,
    "IMH": 6.143922,
    "IML": 1.673317,
    "IMO": 5.339949,
    "IMS": 14.580848,
    "IMT": 66.430905,
    "IMY": 69.48742,
    "IMZ": 69.144287,
    "INH": 13.828384,
    "INV": 42.85292,
    "INZ": 3.072489,
    "IOG": 14.66537,
    "IOH": 48.927375,
    "IOJ": 48.425834,
    "IOL": 62.237327,
    "IOM": 4.06794,
    "ION": 2.73066,
    "IOO": 4.107285,
    "IOP": 5.630822,
    "IOT": 54.809039,
    "IOV": 53.688809,
    "IPA": 0.769631,
    "IPB": 0.846063,
    "IPC": 23.482213,
    "IPE": 9.071604,
    "IPF": 0.114788,
    "IPG": 9.013841,
    "IPJ": 19.653531,
    "IPK": 50.983934,
    "IPO": 45.066388,
    "IPP": 0.168047,
    "IPR": 31.667838,
    "IPU": 46.302799,
    "IPV": 73.102136,
    "IRB": 1.174156,
    "IRE": 44.929312,
    "IRF": 6.417772,
    "IRL": 16.380356,
    "IRO": 1.860518,
    "IRT": 7.047652,
    "IRV": 6.300533,
    "IRY": 3.553772,
    "ISR": 18.15396,
    "ISS": 0.280867,
    "IST": 0.173332,
    "ITA": 67.559374,
    "ITC": 1.247652,
    "ITD": 63.322521,
    "ITJ": 9.723503,
    "ITL": 4.030359,
    "ITP": 11.497922,
    "ITR": 3.962248,
    "ITV": 45.32737,
    "ITZ": 56.344956,
    "IUA": 63.503988,
    "IUB": 66.669197,
    "IUC": 1.870738,
    "IUF": 63.355048,
    "IUH": 5.552584,
    "IUM": 62.60725,
    "IUN": 71.105715,
    "IUV": 62.610491,
    "IUZ": 4.245228,
    "IV2": 19.504277,
    "IV6": 60.734417,
    "IV7": 4.531853,
    "IV8": 2.08034,
    "IVA": 2.521071,
    "IVF": 6.487468,
    "IVS": 5.468876,
    "IVY": 5.486053,
    "IYB": 5.761015,
    "IYP": 3.253631,
    "IYR": 0.12961,
    "IYS": 1.289199,
    "IYV": 1.124328,
    "IZA": 2.015809,
    "IZB": 9.172983,
    "IZE": 60.484399,
    "IZL": 48.856386,
    "IZS": 8.175609,
    "IZV": 9.261111,
    "IZY": 45.196612,
    "JET": 2.17301,
    "JOT": 54.312108,
    "JUP": 0.504419,
    "KAC": 3.497759,
    "KAN": 6701.192106,
    "KAV": 54.586491,
    "KBJ": 4.118156,
    "KBP": 1.620384,
    "KBZ": 48.601859,
    "KCL": 1.682517,
    "KCV": 4.776343,
    "KDE": 1.579297,
    "KDI": 53.508637,
    "KDK": 14.546321,
    "KDL": 49.308455,
    "KDO": 53.391992,
    "KDS": 50.995706,
    "KDT": 50.829595,
    "KDV": 45.494612,
    "KDZ": 46.076555,
    "KEI": 1.743175,
    "KEO": 1.62218,
    "KEU": 50.196791,
    "KFZ": 3.991935,
    "KGM": 3.129581,
    "KH1": 1.303662,
    "KHA": 3.330461,
    "KHB": 1.485263,
    "KHC": 2.164269,
    "KHD": 1.362668,
    "KHF": 0.152594,
    "KHJ": 1.25865,
    "KHP": 1.030709,
    "KHT": 2.725967,
    "KHU": 35.413727,
    "KIA": 4.432012,
    "KIB": 4.018374,
    "KIE": 4.107777,
    "KIH": 1.387854,
    "KIK": 1.38613,
    "KIS": 0.209456,
    "KJK": 0.002123,
    "KKB": 60.008957,
    "KKC": 54.401611,
    "KKE": 48.600016,
    "KKH": 6.377169,
    "KKL": 2.189093,
    "KKO": 45.853274,
    "KKP": 46.439954,
    "KKT": 2.784145,
    "KLH": 3.010915,
    "KLI": 1.168377,
    "KLL": 54.633014,
    "KLM": 62.408664,
    "KLS": 41.080134,
    "KLU": 4.325225,
    "KMA": 159.608656,
    "KME": 1.500618,
    "KMF": 3.411147,
    "KMN": 0.969637,
    "KMT": 3.582228,
    "KNC": 62.866749,
    "KNI": 1.232982,
    "KNJ": 1.941156,
    "KNN": 1.333864,
    "KNP": 76.192046,
    "KNS": 3.988962,
    "KNT": 56.510448,
    "KNV": 67.35657,
    "KNZ": 66.27109,
    "KO4": 52.934874,
    "KOB": 1.262172,
    "KOD": 0.999857,
    "KOP": 7.466212,
    "KOT": 1.406973,
    "KOZ": 60.298942,
    "KP3": 51.010491,
    "KPA": 1.574279,
    "KPB": 6.284528,
    "KPC": 20.13492,
    "KPD": 46.08061,
    "KPF": 1.56469,
    "KPH": 1.336794,
    "KPI": 1.315269,
    "KPK": 9.398544,
    "KPP": 2.817633,
    "KPR": 1.673866,
    "KPU": 3.886453,
    "KRC": 0.131997,
    "KRF": 19.534552,
    "KRH": 1.377111,
    "KRO": 45.27764,
    "KRR": 1.112193,
    "KRS": 0.491695,
    "KRT": 69.635713,
    "KRV": 45.35042,
    "KSA": 3.642796,
    "KSC": 46.350253,
    "KSK": 2.610062,
    "KSL": 53.533541,
    "KSM": 48.256653,
    "KSP": 61.262849,
    "KSR": 4.792787,
    "KST": 2.023521,
    "KSV": 5.159012,
    "KSY": 9.823136,
    "KTE": 41.911942,
    "KTI": 1.99022,
    "KTJ": 2.224707,
    "KTM": 20.456707,
    "KTN": 7.463766,
    "KTR": 9.538299,
    "KTS": 13.964538,
    "KTT": 65.906776,
    "KTU": 27.167022,
    "KTV": 6.921907,
    "KU3": 1.041634,
    "KUA": 1.418146,
    "KUB": 0.700541,
    "KUD": 1.554666,
    "KUP": 46.427547,
    "KUT": 12.284501,
    "KVA": 1.579021,
    "KVK": 1.15751,
    "KVR": 1.155825,
    "KVS": 3.381811,
    "KVT": 1.421055,
    "KYA": 1.225633,
    "KYR": 0.791086,
    "KYS": 49.746947,
    "KZL": 27.624239,
    "KZO": 2.080036,
    "KZU": 2.335369,
    "LAI": 1.716458,
    "LET": 52.208727,
    "LFD": 8.30483,
    "LGK": 1.278167,
    "LGO": 6.169309,
    "LHM": 77.259019,
    "LHP": 53.651568,
    "LKT": 1.683645,
    "LLA": 1.293612,
    "LPH": 1.27793,
    "LRT": 3.286224,
    "LTC": 1.465571,
    "LTS": 4.49416,
    "LZV": 9.14504,
    "MAC": 0.791465,
    "MAD": 1.023199,
    "MAS": 12.793222,
    "MAV": 55.501676,
    "MBL": 0.257907,
    "MBR": 1.505627,
    "MCU": 1.253979,
    "MD1": 1.987882,
    "MD2": 1.901282,
    "MDF": 1.281316,
    "MET": 5.681245,
    "MGB": 1.399355,
    "MGD": 0.933944,
    "MGE": 6.538061,
    "MGH": 2.033208,
    "MHF": 2.000099,
    "MIK": 3.238914,
    "MJB": 7.30245,
    "MJE": 54.731229,
    "MJG": 11.699915,
    "MJH": 4.293239,
    "MJK": 35.889749,
    "MJL": 57.881745,
    "MKA": 1.373717,
    "MKG": 17.293073,
    "MKL": 58.240247,
    "MLS": 16.655738,
    "MLT": 1.31725,
    "MMH": 16.772269,
    "MOD": 56.64912,
    "MOZ": 1.194256,
    "MP2": 1.796319,
    "MP4": 3.09958,
    "MPD": 56.822437,
    "MPE": 1.291245,
    "MPF": 7.466365,
    "MPI": 2.773459,
    "MPK": 8.881611,
    "MPL": 1.844224,
    "MPN": 57.627227,
    "MPP": 22.304371,
    "MPS": 24.790707,
    "MRI": 1.254463,
    "MSK": 3.540382,
    "MSO": 54.666289,
    "MSR": 1.991699,
    "MT1": 42.809304,
    "MT2": 1.2378,
    "MT5": 1.398822,
    "MT6": 1.542387,
    "MT7": 0.686186,
    "MT8": 1.754485,
    "MT9": 0.558924,
    "MTD": 1.379848,
    "MTE": 3.508549,
    "MTF": 1.289288,
    "MTG": 1.457607,
    "MTH": 1.894341,
    "MTI": 0.017374,
    "MTK": 1.538681,
    "MTL": 3.16061,
    "MTS": 2.711393,
    "MTU": 1.305573,
    "MTV": 5.084749,
    "MTX": 4.854499,
    "MUL": 1.772994,
    "MUT": 1.747519,
    "NAK": 1.060924,
    "NAL": 1.887442,
    "NAU": 3.114988,
    "NBE": 1.603646,
    "NBH": 5.959917,
    "NBO": 1.344234,
    "NBZ": 67.67279,
    "NCS": 53.662719,
    "NCU": 56.046085,
    "NDL": 2.074382,
    "NDS": 0.843632,
    "NES": 2.025071,
    "NFF": 1.220889,
    "NFH": 2.123809,
    "NFK": 4.755936,
    "NHP": 5.356837,
    "NHT": 59.767799,
    "NHV": 4.150355,
    "NHY": 5.756618,
    "NIG": 1.010938,
    "NIS": 1.533994,
    "NJF": 12.246799,
    "NJG": 2.733637,
    "NJR": 5.137527,
    "NJY": 6.7198,
    "NKA": 46.383566,
    "NKC": 1.276826,
    "NKH": 1.537622,
    "NKJ": 14.500197,
    "NKK": 7.828514,
    "NKL": 3.159288,
    "NKM": 1.017573,
    "NKP": 1.142797,
    "NKS": 1.751704,
    "NKT": 1.376643,
    "NKV": 2.061595,
    "NLC": 47.685627,
    "NLD": 50.655466,
    "NLE": 1.457383,
    "NLK": 1.674853,
    "NLL": 3.35927,
    "NME": 54.662421,
    "NMG": 121.161403,
    "NMU": 1.106851,
    "NNF": 22.254242,
    "NOA": 1.437908,
    "NOI": 1.310678,
    "NOV": 60.5954,
    "NP1": 4.288194,
    "NPH": 1.763789,
    "NPK": 1.491287,
    "NRC": 11.566691,
    "NRG": 4.969879,
    "NRM": 136.283428,
    "NSA": 2.272329,
    "NSD": 60.351515,
    "NSH": 1.964766,
    "NSK": 6.01513,
    "NSP": 1.645627,
    "NSS": 59.881868,
    "NST": 1.229222,
    "NSY": 1.311373,
    "NTB": 5.544881,
    "NTD": 0.434788,
    "NTF": 2.818522,
    "NTI": 1.412972,
    "NTO": 61.264745,
    "NTS": 2.754978,
    "NUB": 56.541363,
    "NUG": 46.100601,
    "NUH": 1.312752,
    "NVB": 4.305311,
    "NVC": 4.550188,
    "NVK": 43.69769,
    "NVP": 63.91945,
    "NVT": 4.169997,
    "NVZ": 54.713719,
    "NYH": 58.048526,
    "NZH": 3.2755,
    "NZT": 5.418829,
    "NZU": 47.638638,
    "OAB": 71.317702,
    "OBI": 2.843709,
    "OBN": 54.260913,
    "OBP": 0.187544,
    "OBR": 50.403585,
    "OCM": 64.548214,
    "OCN": 47.297814,
    "OCT": 68.647356,
    "ODD": 10.080747,
    "ODG": 1.046594,
    "ODN": 52.649134,
    "ODP": 6.352888,
    "ODS": 65.956421,
    "ODV": 19.439674,
    "OFA": 54.532076,
    "OFB": 10.140752,
    "OFI": 3.847118,
    "OFK": 48.760793,
    "OFO": 64.549549,
    "OFS": 7.813671,
    "OGD": 11.472523,
    "OGF": 8.415389,
    "OGV": 67.061085,
    "OHB": 23.396554,
    "OHI": 0.061112,
    "OHK": 2.692395,
    "OIL": 3.835136,
    "OIR": 4.687976,
    "OIS": 3.152342,
    "OJB": 49.811124,
    "OJH": 10.094097,
    "OJK": 13.110205,
    "OJT": 11.395872,
    "OJU": 64.048023,
    "OJY": 73.974374,
    "OKD": 0.570001,
    "OKF": 4.230275,
    "OKP": 5.793663,
    "OKT": 0.146363,
    "OLA": 51.650157,
    "OLD": 3.151342,
    "OLE": 4.512255,
    "OMB": 59.553127,
    "OMC": 67.107161,
    "OME": 25.409112,
    "OMG": 1.771537,
    "ONB": 48.972168,
    "OND": 45.243686,
    "ONE": 1.480806,
    "ONF": 61.783058,
    "ONK": 56.897527,
    "ONN": 5.773464,
    "ONS": 50.531612,
    "ONT": 49.415591,
    "ONY": 62.437624,
    "OPB": 12.527024,
    "OPD": 7.641379,
    "OPF": 2.938157,
    "OPH": 24.853385,
    "OPI": 24.085768,
    "OPJ": 1.506278,
    "OPL": 9.200517,
    "OPZ": 5.250153,
    "ORC": 1.42806,
    "ORI": 56.625464,
    "OSD": 12.665418,
    "OSF": 99.219891,
    "OSH": 0.533627,
    "OSL": 0.139199,
    "OSN": 1.421238,
    "OTE": 62.900314,
    "OTF": 6.229216,
    "OTJ": 7.431029,
    "OTK": 7.572476,
    "OTM": 1.321151,
    "OTZ": 65.609087,
    "OUB": 6.282789,
    "OUD": 62.395716,
    "OUN": 50.443267,
    "OUR": 78.78993,
    "OUY": 61.707819,
    "OVD": 3.30536,
    "OVR": 65.536155,
    "OVT": 76.847412,
    "OYL": 0.144605,
    "OYS": 9.776317,
    "OYT": 0.122808,
    "OZC": 2.787396,
    "P1A": 1.346383,
    "PAB": 1.248822,
    "PAC": 3.254672,
    "PAF": 3.500742,
    "PAI": 6.229126,
    "PAL": 53.244218,
    "PAO": 1.32647,
    "PAU": 63.49474,
    "PBE": 4.010225,
    "PBF": 1.831276,
    "PBH": 1.425073,
    "PBI": 2.065229,
    "PBK": 55.094189,
    "PBN": 1.487641,
    "PBR": 3.92863,
    "PBS": 64.73436,
    "PBY": 2.813894,
    "PCE": 1.170439,
    "PCH": 3.727361,
    "PCN": 61.13002,
    "PCS": 4.682358,
    "PDC": 0.568769,
    "PDD": 5.420902,
    "PDE": 1.060725,
    "PDF": 56.184046,
    "PDG": 0.187908,
    "PDH": 16.083217,
    "PDS": 0.700411,
    "PEA": 1.449195,
    "PFO": 2.253107,
    "PFS": 2.665596,
    "PGD": 1.588394,
    "PGE": 14.298687,
    "PGH": 7.496113,
    "PGS": 1.262395,
    "PHB": 1.45926,
    "PHE": 2.871541,
    "PHF": 1.011342,
    "PHI": 1.514618,
    "PHK": 1.538106,
    "PHN": 671.038612,
    "PHS": 4.197738,
    "PHY": 7.236804,
    "PID": 1.691104,
    "PIL": 4.095071,
    "PIP": 1.501715,
    "PIR": 1.664271,
    "PIS": 1.28675,
    "PJL": 4.642855,
    "PJP": 46.514759,
    "PKD": 0.861294,
    "PKF": 4.668729,
    "PKH": 1.092897,
    "PKL": 2.242238,
    "PKN": 1.992846,
    "PKP": 1.12059,
    "PKR": 1.396418,
    "PKT": 1.420504,
    "PKU": 7.413548,
    "PKV": 1.807072,
    "PKZ": 8.649154,
    "PLA": 1.126567,
    "PLR": 1.486887,
    "PLS": 25.669238,
    "PMG": 1.569145,
    "PMH": 0.015439,
    "PMP": 1.155787,
    "PNU": 1.073952,
    "PO7": 0.929805,
    "PO8": 4.154081,
    "PO9": 0.825245,
    "POB": 4.928822,
    "POD": 64.453669,
    "POF": 6.623363,
    "POH": 1.13085,
    "POI": 0.100804,
    "POS": 1.21177,
    "POU": 2.474304,
    "PP1": 1.72372,
    "PPB": 10.294195,
    "PPD": 33.449485,
    "PPE": 58.245629,
    "PPF": 4.613923,
    "PPG": 1.301127,
    "PPH": 1.675443,
    "PPI": 2.042416,
    "PPJ": 1.646411,
    "PPK": 2.010053,
    "PPM": 1.958352,
    "PPN": 5.129494,
    "PPO": 1.872186,
    "PPP": 2.786628,
    "PPS": 4.023158,
    "PPT": 2.888396,
    "PPU": 2.017375,
    "PPV": 1.024885,
    "PPZ": 5.87385,
    "PRD": 2.074561,
    "PRF": 59.327193,
    "PRH": 1.951925,
    "PRR": 1.191659,
    "PRU": 3.197496,
    "PRV": 1.199554,
    "PRY": 2.760498,
    "PRZ": 0.0,
    "PSD": 50.093445,
    "PSE": 1.638221,
    "PSG": 8.672803,
    "PSH": 1.015268,
    "PSL": 7.818181,
    "PSO": 0.412975,
    "PSR": 6.547787,
    "PSS": 5.374422,
    "PST": 0.028626,
    "PTC": 61.493744,
    "PTE": 1.515402,
    "PTF": 1.319885,
    "PTG": 59.642746,
    "PTL": 1.664646,
    "PTN": 1.597755,
    "PTO": 1.45154,
    "PTP": 1.067753,
    "PTS": 1.427126,
    "PUA": 9.032565,
    "PUC": 6.573713,
    "PUH": 1.524305,
    "PUK": 1.00407,
    "PUR": 9.311431,
    "PUT": 7.364027,
    "PUV": 53.328333,
    "PVK": 5.182676,
    "PYB": 1.666642,
    "PYD": 0.69962,
    "PYF": 9.457119,
    "PYH": 7.275282,
    "PYI": 5.154474,
    "PYL": 8.795829,
    "PYR": 1.961508,
    "PYS": 55.488878,
    "RAF": 3.621015,
    "RAI": 1.987071,
    "RAN": 54.317644,
    "RAV": 1.348849,
    "RAY": 3.687702,
    "RBA": 21.532178,
    "RBB": 1.490469,
    "RBE": 3.810897,
    "RBF": 1.636376,
    "RBH": 32.200897,
    "RBI": 54.048099,
    "RBK": 8.081588,
    "RBL": 1.681674,
    "RBN": 1.553543,
    "RBP": 2.002772,
    "RBR": 2.903233,
    "RBT": 5.851705,
    "RBV": 6.197855,
    "RCL": 57.502184,
    "RCS": 5.493455,
    "RCV": 1.59925,
    "RD1": 1.754381,
    "RDF": 1.608585,
    "RDH": 4.8033,
    "RDK": 1.275503,
    "RDS": 0.0,
    "RDT": 0.959394,
    "RDZ": 46.948712,
    "RE7": 1.388517,
    "RE8": 3.895826,
    "RGD": 1.029444,
    "RGH": 1.059199,
    "RHD": 1.839666,
    "RHI": 1.602778,
    "RHS": 7.381455,
    "RIA": 1.26356,
    "RIH": 7.091651,
    "RIK": 5.595,
    "RJG": 3.396999,
    "RKC": 1.590721,
    "RKH": 1.037366,
    "RKL": 2.928218,
    "RKS": 1.90562,
    "RKV": 2.328387,
    "RLH": 1.546917,
    "RO1": 1.153002,
    "ROD": 52.247953,
    "ROF": 3.318327,
    "ROS": 0.0,
    "ROY": 1.2506,
    "RPC": 4.938779,
    "RPD": 13.512466,
    "RPE": 0.0,
    "RPG": 6.065501,
    "RPI": 1.374343,
    "RPK": 60.099409,
    "RPL": 1.550033,
    "RPM": 3.741342,
    "RPN": 5.185679,
    "RPO": 6.635205,
    "RPP": 4.423059,
    "RPS": 60.192137,
    "RPT": 4.614878,
    "RPU": 3.292636,
    "RPX": 58.964914,
    "RRA": 1.34066,
    "RRP": 1.472777,
    "RS1": 1.436698,
    "RSF": 3.928716,
    "RSK": 1.689613,
    "RSY": 0.993428,
    "RSZ": 7.322645,
    "RTA": 1.805832,
    "RTB": 2.405881,
    "RTD": 1.852105,
    "RTG": 5.215961,
    "RTH": 6.283366,
    "RTI": 3.022684,
    "RTP": 12.612403,
    "RUH": 3.239238,
    "RUT": 2.253464,
    "RVI": 1.307876,
    "RVS": 2.682957,
    "RYA": 1.345106,
    "RYB": 46.591152,
    "RYD": 1.548607,
    "RYF": 14.178954,
    "RYU": 46.038542,
    "RZR": 4.573131,
    "SAP": 1.651429,
    "SAR": 49.231702,
    "SAS": 1.658446,
    "SAT": 260.073104,
    "SBH": 1.892195,
    "SBI": 4.260272,
    "SBR": 1.351848,
    "SBS": 66.99517,
    "SCZ": 1.401374,
    "SDA": 47.076373,
    "SEH": 1.196428,
    "SER": 54.363388,
    "SFA": 18.200576,
    "SFS": 1.323317,
    "SGT": 1.533523,
    "SHE": 3.684427,
    "SHI": 0.889434,
    "SHU": 1.367262,
    "SIS": 1.668084,
    "SJP": 58.154625,
    "SKL": 1.815253,
    "SKO": 1.713793,
    "SKS": 47.193015,
    "SKT": 0.104786,
    "SKZ": 0.92246,
    "SLF": 10.098232,
    "SLG": 1.324853,
    "SLR": 0.321693,
    "SLS": 0.908569,
    "SMP": 1.03779,
    "SNY": 3.005839,
    "SOS": 1.335797,
    "SPA": 63.343352,
    "SPD": 76.436787,
    "SPE": 99.75717,
    "SPN": 9.062287,
    "SPP": 1.413955,
    "SPR": 1.218507,
    "SPT": 1.982464,
    "SRA": 21.970687,
    "SRE": 59.630762,
    "SRL": 1.448628,
    "SRO": 26.113628,
    "SSD": 51.661671,
    "SSE": 0.00398,
    "SSF": 0.999516,
    "SSK": 1.485921,
    "SSN": 55.027977,
    "SSO": 13.239327,
    "SSS": 1.463417,
    "SST": 1.470519,
    "ST1": 198.491277,
    "STI": 1.23966,
    "STM": 4.730602,
    "STS": 80.415848,
    "STZ": 24.695624,
    "SUA": 0.538334,
    "SUB": 0.39276,
    "SUC": 20.963335,
    "SUR": 1.191885,
    "SVB": 9.257222,
    "SVS": 2.546855,
    "SVY": 1.670604,
    "SYF": 261.333138,
    "SYL": 4388.336322,
    "SYR": 48.324195,
    "SYS": 46.089576,
    "T3B": 0.13953,
    "TAL": 2.765751,
    "TAO": 19.211397,
    "TAR": 2.31049,
    "TAU": 0.646147,
    "TAZ": 2.357189,
    "TB9": 49.886012,
    "TBP": 0.260808,
    "TBT": 49.415292,
    "TBV": 0.368521,
    "TCA": 0.796798,
    "TCB": 0.209318,
    "TCC": 0.077466,
    "TCD": 46.005431,
    "TCF": 4.091558,
    "TCG": 1.311087,
    "TCH": 2.062932,
    "TCI": 10.290411,
    "TCS": 42.588453,
    "TDG": 0.499224,
    "TDP": 55.927183,
    "TE3": 38.569337,
    "TE4": 5.882559,
    "TEJ": 2.34398,
    "TFE": 2.542492,
    "TFF": 36.915795,
    "TFU": 1.175694,
    "TGA": 0.458034,
    "TGE": 0.28695,
    "TGN": 1.292602,
    "TGR": 6.296016,
    "TGT": 0.107565,
    "TGV": 16.681325,
    "TGZ": 5.489319,
    "THD": 2.767399,
    "THF": 2.136407,
    "THG": 6.415251,
    "THH": 130.376654,
    "THO": 47.148846,
    "THS": 59.300367,
    "THT": 0.233256,
    "THV": 75.91037,
    "TI1": 1487.979317,
    "TI2": 0.130094,
    "TI3": 0.12246,
    "TI4": 0.059711,
    "TI6": 0.04911,
    "TI7": 72.697128,
    "TIE": 0.762965,
    "TIL": 1.383484,
    "TIP": 46.84836,
    "TIV": 47.613344,
    "TJB": 9.439641,
    "TJF": 5.203734,
    "TJI": 6.129225,
    "TJL": 21.71873,
    "TJT": 63.689378,
    "TKF": 65.093554,
    "TKH": 2.398935,
    "TKK": 1.713077,
    "TKM": 0.192201,
    "TLE": 26.738948,
    "TLH": 30.662787,
    "TLK": 1.579967,
    "TLT": 65.951018,
    "TLU": 50.018295,
    "TLV": 1.216071,
    "TLY": 5319.937078,
    "TLZ": 18.252081,
    "TMC": 0.147858,
    "TMG": 1.281376,
    "TMH": 0.0,
    "TMM": 66.163412,
    "TMR": 7.038808,
    "TMS": 1.818224,
    "TMU": 1.30814,
    "TMV": 5.227711,
    "TMZ": 1.880216,
    "TNA": 1.56356,
    "TNB": 47.434584,
    "TND": 1.34411,
    "TNF": 3.786176,
    "TNH": 12.247966,
    "TNI": 10.14972,
    "TNK": 30.270403,
    "TNS": 11.816432,
    "TO8": 53.395005,
    "TOK": 55.946632,
    "TOT": 853.432971,
    "TP1": 63.401833,
    "TP2": 1.89125,
    "TPC": 13.505258,
    "TPE": 0.509365,
    "TPF": 9.933502,
    "TPJ": 72.537245,
    "TPL": 19.716596,
    "TPO": 0.165572,
    "TPP": 68.669223,
    "TPR": 0.4973,
    "TPV": 10.208903,
    "TPZ": 26.4301,
    "TRJ": 1.886766,
    "TRN": 1.311434,
    "TRO": 2.484083,
    "TRR": 5.748071,
    "TRU": 1.412437,
    "TSI": 0.185808,
    "TSP": 65.403041,
    "TTA": 0.617204,
    "TTE": 1.589492,
    "TTL": 36.624367,
    "TTP": 48.065255,
    "TTS": 65.286063,
    "TTV": 7.889642,
    "TTZ": 3.600221,
    "TUA": 1.44136,
    "TVE": 1.178677,
    "TVN": 2.530287,
    "TYH": 2.081679,
    "TZC": 0.303143,
    "TZD": 2.433021,
    "TZH": 7.803841,
    "TZL": 0.123188,
    "TZP": 12.594589,
    "TZT": 0.153957,
    "TZV": 849.327576,
    "UAB": 5.023749,
    "UAP": 65.667072,
    "UCN": 2.093534,
    "UCP": 1.182384,
    "UFH": 68.004195,
    "UHL": 68.304649,
    "UHS": 6.014561,
    "ULH": 6.345069,
    "ULL": 66.611336,
    "UNT": 1.396843,
    "UP1": 6.136126,
    "UP2": 3.758126,
    "UPD": 20.5217,
    "UPH": 31.248791,
    "UPP": 6.279446,
    "UPS": 4.66314,
    "URA": 2.019417,
    "URC": 52.582356,
    "URD": 46.388469,
    "URG": 70.741097,
    "URM": 46.509678,
    "URS": 3.564248,
    "URV": 3.412282,
    "USS": 3.41124,
    "UST": 3.742226,
    "USY": 0.2386,
    "UYH": 4.530285,
    "UZY": 2.177647,
    "VAY": 1.565593,
    "VCD": 5.653172,
    "VCG": 5.115124,
    "VCY": 3.317713,
    "VFK": 4.904376,
    "VFS": 1.848005,
    "VK6": 3.704785,
    "VKI": 2.787961,
    "VKT": 0.109004,
    "VMV": 2.489448,
    "VNK": 2.346051,
    "VPP": 48.670685,
    "VPS": 1.440971,
    "VRK": 1.22405,
    "VTF": 2.234068,
    "YA1": 1.272095,
    "YAC": 13.905276,
    "YAE": 1.064604,
    "YAK": 4.838426,
    "YAN": 13.220944,
    "YAR": 26.419222,
    "YAS": 14.95209,
    "YAY": 1597.403768,
    "YBE": 1.696994,
    "YBH": 49.495111,
    "YBJ": 54.710582,
    "YBP": 11.608317,
    "YBR": 51.612279,
    "YBS": 0.130024,
    "YCG": 56.938243,
    "YCH": 2.43634,
    "YCK": 4.300998,
    "YCL": 10.674226,
    "YCP": 8.635543,
    "YCY": 3.711464,
    "YDI": 0.449088,
    "YDK": 0.107086,
    "YDL": 55.543999,
    "YDM": 1.623564,
    "YDP": 2.050806,
    "YDZ": 51.190627,
    "YEF": 0.964137,
    "YFV": 0.097083,
    "YGM": 3.270878,
    "YHB": 2.279911,
    "YHI": 1.489501,
    "YHK": 1.935204,
    "YHP": 4.104181,
    "YHS": 25.650577,
    "YHT": 0.371574,
    "YHY": 1.191287,
    "YHZ": 8.722435,
    "YIK": 1.370127,
    "YIS": 1.270026,
    "YIT": 2.469736,
    "YIV": 3.395665,
    "YJA": 62.892855,
    "YJH": 3.891347,
    "YJK": 5.152961,
    "YJU": 62.249579,
    "YJY": 54.00892,
    "YKS": 0.316072,
    "YKT": 0.872485,
    "YLB": 1.624947,
    "YLC": 3.780484,
    "YLE": 8.591127,
    "YLO": 5.14466,
    "YLR": 12.189845,
    "YLY": 2.45775,
    "YLZ": 3.880697,
    "YMD": 52.854992,
    "YMH": 1.446875,
    "YMP": 1.02359,
    "YNK": 45.343443,
    "YNL": 52.136754,
    "YOA": 83.22655,
    "YOS": 53.430131,
    "YOT": 36.24288,
    "YOZ": 46.167976,
    "YP1": 61.732784,
    "YP2": 68.48226,
    "YP4": 50.855061,
    "YPC": 5.029001,
    "YPD": 63.809954,
    "YPF": 9.240327,
    "YPI": 52.84661,
    "YPK": 13.181403,
    "YPL": 68.372129,
    "YPN": 63.419036,
    "YPP": 24.007188,
    "YPR": 1.62986,
    "YPT": 3.692117,
    "YPU": 62.414336,
    "YPV": 7.641906,
    "YRZ": 45.614704,
    "YSA": 46.158927,
    "YSL": 42.042593,
    "YSO": 1.244371,
    "YSU": 0.160966,
    "YTC": 63.29319,
    "YTD": 0.830937,
    "YTJ": 65.715729,
    "YTO": 50.782472,
    "YTR": 74.867468,
    "YTV": 2.88029,
    "YTY": 55.90397,
    "YUB": 5.424566,
    "YUD": 70.991325,
    "YUI": 1.884056,
    "YUK": 47.245637,
    "YUN": 54.208526,
    "YUY": 1.0075,
    "YVB": 1.24933,
    "YVD": 3.951251,
    "YVF": 69.540363,
    "YVG": 59.735944,
    "YVO": 65.735439,
    "YVS": 70.629905,
    "YZC": 4.471723,
    "YZF": 90.225294,
    "YZG": 14.099459,
    "YZH": 11.105127,
    "YZK": 7.365304,
    "YZL": 4.974783,
    "ZA2": 1.796843,
    "ZAD": 44.038117,
    "ZAV": 54.394275,
    "ZAY": 5.804955,
    "ZBD": 652.840134,
    "ZBI": 2.067089,
    "ZBJ": 4.6105,
    "ZBN": 23.872608,
    "ZBO": 2.901959,
    "ZBZ": 62.760326,
    "ZCA": 7.689982,
    "ZCB": 68.859012,
    "ZCC": 74.037092,
    "ZCD": 4.252205,
    "ZCE": 4.175782,
    "ZCF": 3.762668,
    "ZCG": 5.961538,
    "ZCH": 2.364529,
    "ZCK": 1.704219,
    "ZCN": 3.949729,
    "ZDD": 6.886834,
    "ZDK": 15.180616,
    "ZDZ": 12.896633,
    "ZFB": 6.864792,
    "ZFZ": 64.992525,
    "ZHH": 1.403621,
    "ZJB": 11.561576,
    "ZJH": 57.757633,
    "ZJI": 12.102022,
    "ZJL": 14.456268,
    "ZJR": 6.590431,
    "ZJT": 63.595321,
    "ZJV": 10.738945,
    "ZK1": 47.351609,
    "ZK2": 55.106971,
    "ZKK": 23.751054,
    "ZLB": 47.38578,
    "ZLG": 60.373324,
    "ZLH": 11.580018,
    "ZMT": 58.862526,
    "ZMU": 0.194725,
    "ZMY": 6.274293,
    "ZNF": 52.009625,
    "ZOS": 1.724906,
    "ZP1": 59.303796,
    "ZP2": 5.143584,
    "ZP3": 4.182879,
    "ZP6": 54.708731,
    "ZP7": 63.446496,
    "ZP8": 3.638233,
    "ZP9": 57.410413,
    "ZPA": 62.543693,
    "ZPC": 18.675602,
    "ZPE": 33.441288,
    "ZPF": 21.630402,
    "ZPG": 9.611698,
    "ZPH": 1.35089,
    "ZPJ": 11.993578,
    "ZPK": 7.545493,
    "ZPN": 67.417832,
    "ZPR": 1.373707,
    "ZR2": 1.258538,
    "ZR3": 0.832602,
    "ZSB": 9.546469,
    "ZSF": 51.837683,
    "ZSG": 4.206085,
    "ZSK": 54.954763,
    "ZSN": 52.683107,
    "ZTF": 6.766602,
    "ZTG": 1.213832,
    "ZUD": 3.915185,
    "ZUE": 4.65963,
    "ZUS": 47.303932,
    "ZVB": 86.924903,
    "ZVO": 3.643007,
    "ZYC": 4.384434,
    "ZYD": 4.385229,
    "ZZL": 77.898832
  }
}